sshush/__init__.py
sshush/command_line.py
sshush/sshush.py
sshush-1.5.0.dist-info/LICENSE.md
sshush-1.5.0.dist-info/METADATA
sshush-1.5.0.dist-info/WHEEL
sshush-1.5.0.dist-info/entry_points.txt
sshush-1.5.0.dist-info/top_level.txt
sshush-1.5.0.dist-info/RECORD
