Metadata-Version: 2.1
Name: sshush
Version: 1.5.0
Summary: A small example package
Home-page: http://github.com/bencromwell/sshush
Author: Ben Cromwell
Author-email: Ben Cromwell <author@example.com>
License: MIT
Project-URL: Homepage, https://sshush.bencromwell.com
Project-URL: Bug Tracker, https://github.com/bencromwell/sshush/issues
Classifier: Programming Language :: Python :: 3
Classifier: License :: OSI Approved :: MIT License
Classifier: Operating System :: OS Independent
Requires-Python: >=3.7
License-File: LICENSE.md
Requires-Dist: pyaml
